{
  "initial_funds": 100000.0,
  "final_cash": 37407.075236300974,
  "final_portfolio_value": 99446.07523630097,
  "total_return_pct": -0.005539247636990331,
  "final_positions": {
    "HK.02600": {
      "qty": 2400,
      "available_qty": 2400,
      "avg_price": 10.61
    },
    "HK.02382": {
      "qty": 700,
      "available_qty": 700,
      "avg_price": 52.25
    }
  },
  "trades_count": 176,
  "total_buys": 89,
  "total_sells": 87,
  "total_profit_loss_no_cost": -53728.80000110017,
  "profit_factor": 0.925881724308081,
  "max_drawdown_pct": 0.2510230391161837,
  "equity_curve": [
    {
      "time": "2025-03-24 00:00:00",
      "value": 100000.0
    },
    {
      "time": "2025-03-24 00:00:00",
      "value": 99931.22206249999
    },
    {
      "time": "2025-03-24 00:00:00",
      "value": 99907.90680210001
    },
    {
      "time": "2025-03-25 10:00:00",
      "value": 100962.70530209999
    },
    {
      "time": "2025-03-25 11:30:00",
      "value": 99670.8681967
    },
    {
      "time": "2025-03-25 11:30:00",
      "value": 99606.35688050001
    },
    {
      "time": "2025-03-31 10:30:00",
      "value": 95947.2009643
    },
    {
      "time": "2025-03-31 11:30:00",
      "value": 95888.25965310002
    },
    {
      "time": "2025-04-01 10:00:00",
      "value": 96459.08114690002
    },
    {
      "time": "2025-04-01 16:00:00",
      "value": 96412.48759840001
    },
    {
      "time": "2025-04-03 10:00:00",
      "value": 96374.18384760001
    },
    {
      "time": "2025-04-07 10:00:00",
      "value": 94006.46528510001
    },
    {
      "time": "2025-04-07 10:00:00",
      "value": 90033.64494430002
    },
    {
      "time": "2025-04-07 10:00:00",
      "value": 89974.47050430001
    },
    {
      "time": "2025-04-07 10:00:00",
      "value": 89941.65016350002
    },
    {
      "time": "2025-04-08 13:30:00",
      "value": 87651.6807127
    },
    {
      "time": "2025-04-08 13:30:00",
      "value": 87621.71126190001
    },
    {
      "time": "2025-04-09 14:30:00",
      "value": 87442.58200190001
    },
    {
      "time": "2025-04-14 10:00:00",
      "value": 93065.48156070017
    },
    {
      "time": "2025-04-14 14:30:00",
      "value": 93002.35924430017
    },
    {
      "time": "2025-04-16 11:30:00",
      "value": 89723.44925790015
    },
    {
      "time": "2025-04-16 11:30:00",
      "value": 89664.53927150015
    },
    {
      "time": "2025-04-22 10:30:00",
      "value": 89631.65763650015
    },
    {
      "time": "2025-04-22 12:00:00",
      "value": 90167.52363260016
    },
    {
      "time": "2025-04-25 10:30:00",
      "value": 91043.29938260016
    },
    {
      "time": "2025-04-28 10:00:00",
      "value": 90981.43971260017
    },
    {
      "time": "2025-04-29 10:00:00",
      "value": 92197.09812260017
    },
    {
      "time": "2025-04-30 10:00:00",
      "value": 92133.96737260018
    },
    {
      "time": "2025-05-02 10:30:00",
      "value": 93489.30199260017
    },
    {
      "time": "2025-05-06 11:00:00",
      "value": 93426.23238620016
    },
    {
      "time": "2025-05-07 10:00:00",
      "value": 94691.66203480019
    },
    {
      "time": "2025-05-08 10:00:00",
      "value": 94628.4211209002
    },
    {
      "time": "2025-05-09 11:00:00",
      "value": 94607.9652594002
    },
    {
      "time": "2025-05-12 00:00:00",
      "value": 98666.97139540019
    },
    {
      "time": "2025-05-12 10:00:00",
      "value": 100456.03207330045
    },
    {
      "time": "2025-05-12 10:30:00",
      "value": 100394.34461440044
    },
    {
      "time": "2025-05-15 13:30:00",
      "value": 102254.9323923007
    },
    {
      "time": "2025-05-15 13:30:00",
      "value": 102190.52017090097
    },
    {
      "time": "2025-05-23 15:00:00",
      "value": 98806.35981270098
    },
    {
      "time": "2025-05-23 15:00:00",
      "value": 98737.89083110097
    },
    {
      "time": "2025-05-26 11:30:00",
      "value": 98703.68013510096
    },
    {
      "time": "2025-05-27 10:00:00",
      "value": 98276.34669350098
    },
    {
      "time": "2025-05-28 10:30:00",
      "value": 98226.92416730098
    },
    {
      "time": "2025-05-29 13:30:00",
      "value": 96347.40924330098
    },
    {
      "time": "2025-05-29 13:30:00",
      "value": 96304.99150430098
    },
    {
      "time": "2025-06-04 14:00:00",
      "value": 99503.35202280097
    },
    {
      "time": "2025-06-06 10:00:00",
      "value": 99478.74444780097
    },
    {
      "time": "2025-06-09 11:00:00",
      "value": 100472.75284280098
    },
    {
      "time": "2025-06-16 11:00:00",
      "value": 100428.75755280098
    },
    {
      "time": "2025-06-18 10:30:00",
      "value": 98119.61616480097
    },
    {
      "time": "2025-06-18 11:00:00",
      "value": 98077.00603430098
    },
    {
      "time": "2025-06-20 10:00:00",
      "value": 101282.55641930098
    },
    {
      "time": "2025-06-20 12:00:00",
      "value": 98791.86909030098
    },
    {
      "time": "2025-06-20 12:00:00",
      "value": 98731.556851301
    },
    {
      "time": "2025-06-23 14:30:00",
      "value": 100235.65501330097
    },
    {
      "time": "2025-06-25 16:00:00",
      "value": 100166.87707580096
    },
    {
      "time": "2025-07-02 10:00:00",
      "value": 100138.18518080097
    },
    {
      "time": "2025-07-03 10:30:00",
      "value": 104053.90500830096
    },
    {
      "time": "2025-07-07 10:00:00",
      "value": 103996.25239730097
    },
    {
      "time": "2025-07-08 10:00:00",
      "value": 104020.56891330096
    },
    {
      "time": "2025-07-08 10:00:00",
      "value": 104665.62288080096
    },
    {
      "time": "2025-07-09 10:00:00",
      "value": 104597.02942830097
    },
    {
      "time": "2025-07-10 10:00:00",
      "value": 107604.27635580096
    },
    {
      "time": "2025-07-21 10:00:00",
      "value": 107553.45127580097
    },
    {
      "time": "2025-07-22 00:00:00",
      "value": 104786.65027580096
    },
    {
      "time": "2025-07-22 10:00:00",
      "value": 104759.45159580096
    },
    {
      "time": "2025-07-22 10:30:00",
      "value": 104707.44579580096
    },
    {
      "time": "2025-07-23 10:30:00",
      "value": 106917.40375580096
    },
    {
      "time": "2025-07-24 10:00:00",
      "value": 107240.25676830095
    },
    {
      "time": "2025-07-28 10:00:00",
      "value": 107168.79360080096
    },
    {
      "time": "2025-08-05 10:00:00",
      "value": 107307.25136830096
    },
    {
      "time": "2025-08-06 10:00:00",
      "value": 107237.18352580097
    },
    {
      "time": "2025-08-20 14:00:00",
      "value": 113737.63831330097
    },
    {
      "time": "2025-08-21 10:00:00",
      "value": 113669.12204330097
    },
    {
      "time": "2025-08-21 13:30:00",
      "value": 113625.23217330096
    },
    {
      "time": "2025-08-22 12:00:00",
      "value": 114619.95074330097
    },
    {
      "time": "2025-08-22 15:30:00",
      "value": 115719.99396830097
    },
    {
      "time": "2025-08-27 11:00:00",
      "value": 115649.95059830097
    },
    {
      "time": "2025-08-29 11:00:00",
      "value": 115609.89593330097
    },
    {
      "time": "2025-08-29 12:00:00",
      "value": 115530.34507330097
    },
    {
      "time": "2025-09-01 10:00:00",
      "value": 115496.07752580097
    },
    {
      "time": "2025-09-03 10:00:00",
      "value": 116263.20739380097
    },
    {
      "time": "2025-09-03 15:00:00",
      "value": 116200.25585780098
    },
    {
      "time": "2025-09-05 10:30:00",
      "value": 115214.65220780097
    },
    {
      "time": "2025-09-10 14:00:00",
      "value": 114940.47502030098
    },
    {
      "time": "2025-09-15 14:00:00",
      "value": 114862.19335780098
    },
    {
      "time": "2025-09-17 10:00:00",
      "value": 115692.56908030098
    },
    {
      "time": "2025-09-18 14:30:00",
      "value": 115614.23470780098
    },
    {
      "time": "2025-09-22 10:00:00",
      "value": 117981.97791030098
    },
    {
      "time": "2025-09-23 10:00:00",
      "value": 117900.96809680098
    },
    {
      "time": "2025-09-23 14:00:00",
      "value": 117865.50853430099
    },
    {
      "time": "2025-09-24 14:00:00",
      "value": 118279.87954680098
    },
    {
      "time": "2025-09-25 14:00:00",
      "value": 117880.98946030097
    },
    {
      "time": "2025-09-26 10:00:00",
      "value": 117799.92656030098
    },
    {
      "time": "2025-09-29 10:30:00",
      "value": 117760.10030280097
    },
    {
      "time": "2025-09-30 13:30:00",
      "value": 118205.09106630099
    },
    {
      "time": "2025-10-03 10:00:00",
      "value": 118164.05359230097
    },
    {
      "time": "2025-10-09 10:00:00",
      "value": 118430.90015630098
    },
    {
      "time": "2025-10-09 15:00:00",
      "value": 118389.94701830098
    },
    {
      "time": "2025-10-10 10:00:00",
      "value": 118377.29026580098
    },
    {
      "time": "2025-10-13 11:00:00",
      "value": 117760.67979580098
    },
    {
      "time": "2025-10-13 11:30:00",
      "value": 113485.19819580099
    },
    {
      "time": "2025-10-13 11:30:00",
      "value": 113430.411158301
    },
    {
      "time": "2025-10-14 10:00:00",
      "value": 112746.70048630098
    },
    {
      "time": "2025-10-14 13:30:00",
      "value": 112695.88143030097
    },
    {
      "time": "2025-10-24 10:00:00",
      "value": 111425.52208080098
    },
    {
      "time": "2025-10-24 14:00:00",
      "value": 111376.11642180098
    },
    {
      "time": "2025-11-03 10:00:00",
      "value": 108675.32710930098
    },
    {
      "time": "2025-11-03 10:00:00",
      "value": 108634.29565930099
    },
    {
      "time": "2025-11-05 11:00:00",
      "value": 106476.06238930099
    },
    {
      "time": "2025-11-06 11:00:00",
      "value": 105022.18608930099
    },
    {
      "time": "2025-11-06 11:30:00",
      "value": 104949.576463301
    },
    {
      "time": "2025-11-07 10:00:00",
      "value": 104920.867625801
    },
    {
      "time": "2025-11-11 10:00:00",
      "value": 100099.048633801
    },
    {
      "time": "2025-11-11 10:00:00",
      "value": 100639.12519130099
    },
    {
      "time": "2025-11-11 10:00:00",
      "value": 100570.384527301
    },
    {
      "time": "2025-11-11 13:30:00",
      "value": 100541.58532980099
    },
    {
      "time": "2025-11-13 10:00:00",
      "value": 96269.429354301
    },
    {
      "time": "2025-11-13 10:00:00",
      "value": 96246.241953301
    },
    {
      "time": "2025-11-14 10:00:00",
      "value": 94838.576381301
    },
    {
      "time": "2025-11-14 10:00:00",
      "value": 94805.562971301
    },
    {
      "time": "2025-11-20 13:30:00",
      "value": 93338.30593380099
    },
    {
      "time": "2025-11-20 13:30:00",
      "value": 93293.210871301
    },
    {
      "time": "2025-12-01 14:30:00",
      "value": 94746.551058801
    },
    {
      "time": "2025-12-03 10:00:00",
      "value": 93035.17016880099
    },
    {
      "time": "2025-12-03 10:00:00",
      "value": 92970.69002680099
    },
    {
      "time": "2025-12-11 12:00:00",
      "value": 92943.19014680099
    },
    {
      "time": "2025-12-12 10:00:00",
      "value": 93049.639439301
    },
    {
      "time": "2025-12-15 10:00:00",
      "value": 93022.111321801
    },
    {
      "time": "2025-12-16 10:00:00",
      "value": 88948.142827301
    },
    {
      "time": "2025-12-16 10:00:00",
      "value": 88900.236783801
    },
    {
      "time": "2025-12-17 10:00:00",
      "value": 88737.759493801
    },
    {
      "time": "2025-12-18 14:30:00",
      "value": 88702.015673801
    },
    {
      "time": "2025-12-22 10:00:00",
      "value": 89185.076073801
    },
    {
      "time": "2025-12-29 13:30:00",
      "value": 89149.294603801
    },
    {
      "time": "2026-01-12 11:00:00",
      "value": 91870.34452580099
    },
    {
      "time": "2026-01-13 14:30:00",
      "value": 91825.010385801
    },
    {
      "time": "2026-01-14 12:00:00",
      "value": 93545.01059380098
    },
    {
      "time": "2026-01-16 10:00:00",
      "value": 94088.01075380098
    },
    {
      "time": "2026-01-19 10:00:00",
      "value": 94024.82729380098
    },
    {
      "time": "2026-01-19 14:00:00",
      "value": 93991.79957680097
    },
    {
      "time": "2026-01-20 10:30:00",
      "value": 94261.65740380097
    },
    {
      "time": "2026-01-20 13:30:00",
      "value": 95037.15768380098
    },
    {
      "time": "2026-01-20 16:00:00",
      "value": 94971.35977580099
    },
    {
      "time": "2026-01-23 10:00:00",
      "value": 95133.47602580098
    },
    {
      "time": "2026-01-26 10:00:00",
      "value": 95073.01732830098
    },
    {
      "time": "2026-01-26 11:00:00",
      "value": 95037.38721130099
    },
    {
      "time": "2026-01-27 14:30:00",
      "value": 95605.69131880098
    },
    {
      "time": "2026-02-02 10:00:00",
      "value": 95563.32101880098
    },
    {
      "time": "2026-02-03 10:30:00",
      "value": 95570.93189380098
    },
    {
      "time": "2026-02-04 10:00:00",
      "value": 95529.75925630098
    },
    {
      "time": "2026-02-13 11:30:00",
      "value": 95871.98682230098
    },
    {
      "time": "2026-02-16 12:00:00",
      "value": 95082.09655980098
    },
    {
      "time": "2026-02-20 10:00:00",
      "value": 95016.22561080099
    },
    {
      "time": "2026-02-23 10:00:00",
      "value": 94984.56611080098
    },
    {
      "time": "2026-02-23 10:30:00",
      "value": 96375.14622480098
    },
    {
      "time": "2026-02-25 16:00:00",
      "value": 96324.45668480097
    },
    {
      "time": "2026-03-03 14:30:00",
      "value": 94674.40711480098
    },
    {
      "time": "2026-03-03 14:30:00",
      "value": 94637.34515230099
    },
    {
      "time": "2026-03-04 10:30:00",
      "value": 94107.83633230098
    },
    {
      "time": "2026-03-05 10:00:00",
      "value": 94444.63318230098
    },
    {
      "time": "2026-03-05 11:30:00",
      "value": 94390.94968230098
    },
    {
      "time": "2026-03-05 14:00:00",
      "value": 94353.84065730099
    },
    {
      "time": "2026-03-06 14:30:00",
      "value": 95090.43984480097
    },
    {
      "time": "2026-03-10 10:00:00",
      "value": 97752.73226480099
    },
    {
      "time": "2026-03-10 16:00:00",
      "value": 97685.45544880099
    },
    {
      "time": "2026-03-13 11:00:00",
      "value": 103086.11691880098
    },
    {
      "time": "2026-03-16 11:30:00",
      "value": 103018.83106680098
    },
    {
      "time": "2026-03-17 10:00:00",
      "value": 105028.76209480097
    },
    {
      "time": "2026-03-17 14:30:00",
      "value": 104972.37077480098
    },
    {
      "time": "2026-03-18 13:30:00",
      "value": 105454.77614480097
    },
    {
      "time": "2026-03-18 16:00:00",
      "value": 105383.47863730097
    },
    {
      "time": "2026-03-20 00:00:00",
      "value": 105346.52887180097
    },
    {
      "time": "2026-03-23 10:00:00",
      "value": 103288.34114230097
    },
    {
      "time": "2026-03-23 10:00:00",
      "value": 103252.75394630097
    },
    {
      "time": "2026-03-23 11:30:00",
      "value": 99496.84572380097
    },
    {
      "time": "2026-03-23 14:30:00",
      "value": 99446.07523630097
    }
  ],
  "trade_log": [
    {
      "time": "2025-03-24 00:00:00",
      "code": "HK.06683",
      "action": "BUY",
      "qty": 12500,
      "price": 3.99,
      "amount": 49875.0,
      "cost": 68.77793750000001,
      "funds_after": 50056.2220625
    },
    {
      "time": "2025-03-24 00:00:00",
      "code": "HK.02382",
      "action": "BUY",
      "qty": 200,
      "price": 83.868,
      "amount": 16773.6,
      "cost": 23.3152604,
      "funds_after": 33259.3068021
    },
    {
      "time": "2025-03-25 10:00:00",
      "code": "HK.06683",
      "action": "SELL",
      "qty": 12500,
      "price": 4.08,
      "amount": 51000.0,
      "cost": 70.2015,
      "funds_after": 84189.1053021
    },
    {
      "time": "2025-03-25 11:30:00",
      "code": "HK.02382",
      "action": "SELL",
      "qty": 200,
      "price": 77.518,
      "amount": 15503.6,
      "cost": 21.837105400000002,
      "funds_after": 99670.8681967
    },
    {
      "time": "2025-03-25 11:30:00",
      "code": "HK.02382",
      "action": "BUY",
      "qty": 600,
      "price": 77.518,
      "amount": 46510.8,
      "cost": 64.5113162,
      "funds_after": 53095.5568805
    },
    {
      "time": "2025-03-31 10:30:00",
      "code": "HK.02382",
      "action": "SELL",
      "qty": 600,
      "price": 71.518,
      "amount": 42910.8,
      "cost": 59.15591619999999,
      "funds_after": 95947.2009643
    },
    {
      "time": "2025-03-31 11:30:00",
      "code": "HK.02382",
      "action": "BUY",
      "qty": 600,
      "price": 70.568,
      "amount": 42340.799999999996,
      "cost": 58.941311199999994,
      "funds_after": 53547.45965310001
    },
    {
      "time": "2025-04-01 10:00:00",
      "code": "HK.02382",
      "action": "SELL",
      "qty": 600,
      "price": 71.618,
      "amount": 42970.799999999996,
      "cost": 59.1785062,
      "funds_after": 96459.08114690002
    },
    {
      "time": "2025-04-01 16:00:00",
      "code": "HK.06683",
      "action": "BUY",
      "qty": 8300,
      "price": 4.03,
      "amount": 33449.0,
      "cost": 46.5935485,
      "funds_after": 62963.48759840002
    },
    {
      "time": "2025-04-03 10:00:00",
      "code": "HK.02382",
      "action": "BUY",
      "qty": 400,
      "price": 68.418,
      "amount": 27367.200000000004,
      "cost": 38.3037508,
      "funds_after": 35557.983847600015
    },
    {
      "time": "2025-04-07 10:00:00",
      "code": "HK.06683",
      "action": "SELL",
      "qty": 8300,
      "price": 3.75,
      "amount": 31125.0,
      "cost": 43.718562500000004,
      "funds_after": 66639.26528510002
    },
    {
      "time": "2025-04-07 10:00:00",
      "code": "HK.02382",
      "action": "SELL",
      "qty": 400,
      "price": 58.568,
      "amount": 23427.2,
      "cost": 32.820340800000004,
      "funds_after": 90033.64494430002
    },
    {
      "time": "2025-04-07 10:00:00",
      "code": "HK.09961",
      "action": "BUY",
      "qty": 100,
      "price": 429.6,
      "amount": 42960.0,
      "cost": 59.17444,
      "funds_after": 47014.470504300014
    },
    {
      "time": "2025-04-07 10:00:00",
      "code": "HK.02382",
      "action": "BUY",
      "qty": 400,
      "price": 58.568,
      "amount": 23427.2,
      "cost": 32.820340800000004,
      "funds_after": 23554.450163500012
    },
    {
      "time": "2025-04-08 13:30:00",
      "code": "HK.02382",
      "action": "SELL",
      "qty": 400,
      "price": 52.918,
      "amount": 21167.2,
      "cost": 29.9694508,
      "funds_after": 44691.680712700014
    },
    {
      "time": "2025-04-08 13:30:00",
      "code": "HK.02382",
      "action": "BUY",
      "qty": 400,
      "price": 52.918,
      "amount": 21167.2,
      "cost": 29.9694508,
      "funds_after": 23494.511261900014
    },
    {
      "time": "2025-04-09 14:30:00",
      "code": "HK.09961",
      "action": "SELL",
      "qty": 100,
      "price": 428.4,
      "amount": 42840.0,
      "cost": 59.129259999999995,
      "funds_after": 66275.38200190001
    },
    {
      "time": "2025-04-14 10:00:00",
      "code": "HK.02382",
      "action": "SELL",
      "qty": 400,
      "price": 67.067999999,
      "amount": 26827.199999599998,
      "cost": 37.100440799849395,
      "funds_after": 93065.48156070017
    },
    {
      "time": "2025-04-14 14:30:00",
      "code": "HK.02382",
      "action": "BUY",
      "qty": 700,
      "price": 64.968,
      "amount": 45477.600000000006,
      "cost": 63.1223164,
      "funds_after": 47524.75924430016
    },
    {
      "time": "2025-04-16 11:30:00",
      "code": "HK.02382",
      "action": "SELL",
      "qty": 700,
      "price": 60.368,
      "amount": 42257.6,
      "cost": 58.909986399999994,
      "funds_after": 89723.44925790015
    },
    {
      "time": "2025-04-16 11:30:00",
      "code": "HK.02382",
      "action": "BUY",
      "qty": 700,
      "price": 60.368,
      "amount": 42257.6,
      "cost": 58.909986399999994,
      "funds_after": 47406.93927150015
    },
    {
      "time": "2025-04-22 10:30:00",
      "code": "HK.06683",
      "action": "BUY",
      "qty": 7000,
      "price": 3.37,
      "amount": 23590.0,
      "cost": 32.881635,
      "funds_after": 23784.05763650015
    },
    {
      "time": "2025-04-22 12:00:00",
      "code": "HK.02382",
      "action": "SELL",
      "qty": 700,
      "price": 61.218,
      "amount": 42852.600000000006,
      "cost": 59.1340039,
      "funds_after": 66577.52363260016
    },
    {
      "time": "2025-04-25 10:30:00",
      "code": "HK.06683",
      "action": "SELL",
      "qty": 7000,
      "price": 3.5,
      "amount": 24500.0,
      "cost": 34.224250000000005,
      "funds_after": 91043.29938260016
    },
    {
      "time": "2025-04-28 10:00:00",
      "code": "HK.09961",
      "action": "BUY",
      "qty": 100,
      "price": 447.8,
      "amount": 44780.0,
      "cost": 61.85967,
      "funds_after": 46201.439712600164
    },
    {
      "time": "2025-04-29 10:00:00",
      "code": "HK.09961",
      "action": "SELL",
      "qty": 100,
      "price": 460.6,
      "amount": 46060.0,
      "cost": 64.34159,
      "funds_after": 92197.09812260017
    },
    {
      "time": "2025-04-30 10:00:00",
      "code": "HK.09961",
      "action": "BUY",
      "qty": 100,
      "price": 455.0,
      "amount": 45500.0,
      "cost": 63.13074999999999,
      "funds_after": 46633.96737260018
    },
    {
      "time": "2025-05-02 10:30:00",
      "code": "HK.09961",
      "action": "SELL",
      "qty": 100,
      "price": 469.2,
      "amount": 46920.0,
      "cost": 64.66538,
      "funds_after": 93489.30199260017
    },
    {
      "time": "2025-05-06 11:00:00",
      "code": "HK.02382",
      "action": "BUY",
      "qty": 700,
      "price": 64.768,
      "amount": 45337.6,
      "cost": 63.0696064,
      "funds_after": 48088.632386200174
    },
    {
      "time": "2025-05-07 10:00:00",
      "code": "HK.02382",
      "action": "SELL",
      "qty": 700,
      "price": 66.668,
      "amount": 46667.600000000006,
      "cost": 64.5703514,
      "funds_after": 94691.66203480019
    },
    {
      "time": "2025-05-08 10:00:00",
      "code": "HK.02382",
      "action": "BUY",
      "qty": 700,
      "price": 65.418,
      "amount": 45792.600000000006,
      "cost": 63.2409139,
      "funds_after": 48835.82112090018
    },
    {
      "time": "2025-05-09 11:00:00",
      "code": "HK.06683",
      "action": "BUY",
      "qty": 4300,
      "price": 3.37,
      "amount": 14491.0,
      "cost": 20.4558615,
      "funds_after": 34324.36525940018
    },
    {
      "time": "2025-05-12 00:00:00",
      "code": "HK.06683",
      "action": "SELL",
      "qty": 4300,
      "price": 4.32,
      "amount": 18576.0,
      "cost": 25.993864000000002,
      "funds_after": 52874.37139540019
    },
    {
      "time": "2025-05-12 10:00:00",
      "code": "HK.02382",
      "action": "SELL",
      "qty": 700,
      "price": 68.067999999,
      "amount": 47647.59999929999,
      "cost": 65.93932139973644,
      "funds_after": 100456.03207330045
    },
    {
      "time": "2025-05-12 10:30:00",
      "code": "HK.02382",
      "action": "BUY",
      "qty": 700,
      "price": 63.318,
      "amount": 44322.6,
      "cost": 61.687458899999996,
      "funds_after": 56071.74461440045
    },
    {
      "time": "2025-05-15 13:30:00",
      "code": "HK.02382",
      "action": "SELL",
      "qty": 700,
      "price": 66.067999999,
      "amount": 46247.59999929999,
      "cost": 64.41222139973645,
      "funds_after": 102254.9323923007
    },
    {
      "time": "2025-05-15 13:30:00",
      "code": "HK.02382",
      "action": "BUY",
      "qty": 700,
      "price": 66.067999999,
      "amount": 46247.59999929999,
      "cost": 64.41222139973645,
      "funds_after": 55942.92017160097
    },
    {
      "time": "2025-05-23 15:00:00",
      "code": "HK.02382",
      "action": "SELL",
      "qty": 700,
      "price": 61.318,
      "amount": 42922.6,
      "cost": 59.1603589,
      "funds_after": 98806.35981270098
    },
    {
      "time": "2025-05-23 15:00:00",
      "code": "HK.02382",
      "action": "BUY",
      "qty": 800,
      "price": 61.318,
      "amount": 49054.4,
      "cost": 68.46898159999999,
      "funds_after": 49683.49083110097
    },
    {
      "time": "2025-05-26 11:30:00",
      "code": "HK.06683",
      "action": "BUY",
      "qty": 4400,
      "price": 5.56,
      "amount": 24464.0,
      "cost": 34.210696,
      "funds_after": 25185.280135100973
    },
    {
      "time": "2025-05-27 10:00:00",
      "code": "HK.02382",
      "action": "SELL",
      "qty": 800,
      "price": 60.868,
      "amount": 48694.4,
      "cost": 67.3334416,
      "funds_after": 73812.34669350098
    },
    {
      "time": "2025-05-28 10:30:00",
      "code": "HK.02382",
      "action": "BUY",
      "qty": 600,
      "price": 59.418,
      "amount": 35650.8,
      "cost": 49.4225262,
      "funds_after": 38112.12416730097
    },
    {
      "time": "2025-05-29 13:30:00",
      "code": "HK.06683",
      "action": "SELL",
      "qty": 4400,
      "price": 5.14,
      "amount": 22616.0,
      "cost": 31.514924,
      "funds_after": 60696.609243300976
    },
    {
      "time": "2025-05-29 13:30:00",
      "code": "HK.06683",
      "action": "BUY",
      "qty": 5900,
      "price": 5.14,
      "amount": 30325.999999999996,
      "cost": 42.417739000000005,
      "funds_after": 30328.19150430098
    },
    {
      "time": "2025-06-04 14:00:00",
      "code": "HK.06683",
      "action": "SELL",
      "qty": 5900,
      "price": 5.69,
      "amount": 33571.0,
      "cost": 46.639481499999995,
      "funds_after": 63852.55202280098
    },
    {
      "time": "2025-06-06 10:00:00",
      "code": "HK.06683",
      "action": "BUY",
      "qty": 3000,
      "price": 5.85,
      "amount": 17550.0,
      "cost": 24.607575,
      "funds_after": 46277.944447800975
    },
    {
      "time": "2025-06-09 11:00:00",
      "code": "HK.06683",
      "action": "SELL",
      "qty": 3000,
      "price": 6.19,
      "amount": 18570.0,
      "cost": 25.991605,
      "funds_after": 64821.95284280098
    },
    {
      "time": "2025-06-16 11:00:00",
      "code": "HK.06683",
      "action": "BUY",
      "qty": 5400,
      "price": 5.9,
      "amount": 31860.000000000004,
      "cost": 43.99529,
      "funds_after": 32917.957552800974
    },
    {
      "time": "2025-06-18 10:30:00",
      "code": "HK.06683",
      "action": "SELL",
      "qty": 5400,
      "price": 5.48,
      "amount": 29592.000000000004,
      "cost": 41.141388,
      "funds_after": 62468.81616480098
    },
    {
      "time": "2025-06-18 11:00:00",
      "code": "HK.06683",
      "action": "BUY",
      "qty": 5700,
      "price": 5.41,
      "amount": 30837.0,
      "cost": 42.610130500000004,
      "funds_after": 31589.206034300976
    },
    {
      "time": "2025-06-20 10:00:00",
      "code": "HK.02382",
      "action": "SELL",
      "qty": 600,
      "price": 64.85,
      "amount": 38910.0,
      "cost": 53.649615,
      "funds_after": 70445.55641930098
    },
    {
      "time": "2025-06-20 12:00:00",
      "code": "HK.06683",
      "action": "SELL",
      "qty": 5700,
      "price": 4.98,
      "amount": 28386.000000000004,
      "cost": 39.687329,
      "funds_after": 98791.86909030098
    },
    {
      "time": "2025-06-20 12:00:00",
      "code": "HK.06683",
      "action": "BUY",
      "qty": 8700,
      "price": 4.98,
      "amount": 43326.00000000001,
      "cost": 60.312239,
      "funds_after": 55405.55685130098
    },
    {
      "time": "2025-06-23 14:30:00",
      "code": "HK.06683",
      "action": "SELL",
      "qty": 8700,
      "price": 5.16,
      "amount": 44892.0,
      "cost": 61.901838,
      "funds_after": 100235.65501330097
    },
    {
      "time": "2025-06-25 16:00:00",
      "code": "HK.06683",
      "action": "BUY",
      "qty": 9500,
      "price": 5.25,
      "amount": 49875.0,
      "cost": 68.77793750000001,
      "funds_after": 50291.87707580097
    },
    {
      "time": "2025-07-02 10:00:00",
      "code": "HK.02382",
      "action": "BUY",
      "qty": 300,
      "price": 68.1,
      "amount": 20430.0,
      "cost": 28.691895,
      "funds_after": 29833.18518080097
    },
    {
      "time": "2025-07-03 10:30:00",
      "code": "HK.06683",
      "action": "SELL",
      "qty": 9500,
      "price": 5.67,
      "amount": 53865.0,
      "cost": 74.28017249999999,
      "funds_after": 83623.90500830096
    },
    {
      "time": "2025-07-07 10:00:00",
      "code": "HK.06683",
      "action": "BUY",
      "qty": 8200,
      "price": 5.07,
      "amount": 41574.0,
      "cost": 57.652611,
      "funds_after": 41992.25239730097
    },
    {
      "time": "2025-07-08 10:00:00",
      "code": "HK.06683",
      "action": "SELL",
      "qty": 8200,
      "price": 5.08,
      "amount": 41656.0,
      "cost": 57.683484,
      "funds_after": 83590.56891330096
    },
    {
      "time": "2025-07-08 10:00:00",
      "code": "HK.02382",
      "action": "SELL",
      "qty": 300,
      "price": 70.35,
      "amount": 21105.0,
      "cost": 29.946032499999998,
      "funds_after": 104665.62288080096
    },
    {
      "time": "2025-07-09 10:00:00",
      "code": "HK.02382",
      "action": "BUY",
      "qty": 700,
      "price": 70.55,
      "amount": 49385.0,
      "cost": 68.5934525,
      "funds_after": 55212.029428300964
    },
    {
      "time": "2025-07-10 10:00:00",
      "code": "HK.02382",
      "action": "SELL",
      "qty": 700,
      "price": 74.95,
      "amount": 52465.0,
      "cost": 72.75307249999999,
      "funds_after": 107604.27635580096
    },
    {
      "time": "2025-07-21 10:00:00",
      "code": "HK.06683",
      "action": "BUY",
      "qty": 3400,
      "price": 10.8,
      "amount": 36720.0,
      "cost": 50.82508,
      "funds_after": 70833.45127580097
    },
    {
      "time": "2025-07-22 00:00:00",
      "code": "HK.06683",
      "action": "SELL",
      "qty": 3400,
      "price": 10.0,
      "amount": 34000.0,
      "cost": 46.801,
      "funds_after": 104786.65027580096
    },
    {
      "time": "2025-07-22 10:00:00",
      "code": "HK.06683",
      "action": "BUY",
      "qty": 2000,
      "price": 9.56,
      "amount": 19120.0,
      "cost": 27.19868,
      "funds_after": 85639.45159580096
    },
    {
      "time": "2025-07-22 10:30:00",
      "code": "HK.02382",
      "action": "BUY",
      "qty": 500,
      "price": 74.4,
      "amount": 37200.0,
      "cost": 52.005799999999994,
      "funds_after": 48387.44579580096
    },
    {
      "time": "2025-07-23 10:30:00",
      "code": "HK.06683",
      "action": "SELL",
      "qty": 2000,
      "price": 10.68,
      "amount": 21360.0,
      "cost": 30.04204,
      "funds_after": 69717.40375580096
    },
    {
      "time": "2025-07-24 10:00:00",
      "code": "HK.02382",
      "action": "SELL",
      "qty": 500,
      "price": 75.15,
      "amount": 37575.0,
      "cost": 52.1469875,
      "funds_after": 107240.25676830095
    },
    {
      "time": "2025-07-28 10:00:00",
      "code": "HK.02382",
      "action": "BUY",
      "qty": 700,
      "price": 73.85,
      "amount": 51694.99999999999,
      "cost": 71.4631675,
      "funds_after": 55473.793600800964
    },
    {
      "time": "2025-08-05 10:00:00",
      "code": "HK.02382",
      "action": "SELL",
      "qty": 700,
      "price": 74.15,
      "amount": 51905.00000000001,
      "cost": 71.5422325,
      "funds_after": 107307.25136830096
    },
    {
      "time": "2025-08-06 10:00:00",
      "code": "HK.02382",
      "action": "BUY",
      "qty": 700,
      "price": 72.35,
      "amount": 50644.99999999999,
      "cost": 70.0678425,
      "funds_after": 56592.18352580097
    },
    {
      "time": "2025-08-20 14:00:00",
      "code": "HK.02382",
      "action": "SELL",
      "qty": 700,
      "price": 81.75,
      "amount": 57225.0,
      "cost": 79.54521249999998,
      "funds_after": 113737.63831330097
    },
    {
      "time": "2025-08-21 10:00:00",
      "code": "HK.09961",
      "action": "BUY",
      "qty": 100,
      "price": 491.8,
      "amount": 49180.0,
      "cost": 68.51627,
      "funds_after": 64489.122043300966
    },
    {
      "time": "2025-08-21 13:30:00",
      "code": "HK.02382",
      "action": "BUY",
      "qty": 400,
      "price": 78.95,
      "amount": 31580.0,
      "cost": 43.889869999999995,
      "funds_after": 32865.23217330097
    },
    {
      "time": "2025-08-22 12:00:00",
      "code": "HK.02382",
      "action": "SELL",
      "qty": 400,
      "price": 81.55,
      "amount": 32620.0,
      "cost": 45.28143,
      "funds_after": 65439.95074330097
    },
    {
      "time": "2025-08-22 15:30:00",
      "code": "HK.09961",
      "action": "SELL",
      "qty": 100,
      "price": 503.5,
      "amount": 50350.0,
      "cost": 69.95677500000001,
      "funds_after": 115719.99396830097
    },
    {
      "time": "2025-08-27 11:00:00",
      "code": "HK.02382",
      "action": "BUY",
      "qty": 600,
      "price": 84.3,
      "amount": 50580.0,
      "cost": 70.04337000000001,
      "funds_after": 65069.95059830097
    },
    {
      "time": "2025-08-29 11:00:00",
      "code": "HK.02382",
      "action": "SELL",
      "qty": 600,
      "price": 84.35,
      "amount": 50610.0,
      "cost": 70.054665,
      "funds_after": 115609.89593330097
    },
    {
      "time": "2025-08-29 12:00:00",
      "code": "HK.06683",
      "action": "BUY",
      "qty": 5300,
      "price": 10.8,
      "amount": 57240.00000000001,
      "cost": 79.55086,
      "funds_after": 58290.34507330096
    },
    {
      "time": "2025-09-01 10:00:00",
      "code": "HK.02382",
      "action": "BUY",
      "qty": 300,
      "price": 82.05,
      "amount": 24615.0,
      "cost": 34.267547500000006,
      "funds_after": 33641.07752580096
    },
    {
      "time": "2025-09-03 10:00:00",
      "code": "HK.06683",
      "action": "SELL",
      "qty": 5300,
      "price": 10.96,
      "amount": 58088.00000000001,
      "cost": 80.870132,
      "funds_after": 91648.20739380097
    },
    {
      "time": "2025-09-03 15:00:00",
      "code": "HK.06683",
      "action": "BUY",
      "qty": 4200,
      "price": 10.72,
      "amount": 45024.0,
      "cost": 62.951536,
      "funds_after": 46561.25585780097
    },
    {
      "time": "2025-09-05 10:30:00",
      "code": "HK.06683",
      "action": "SELL",
      "qty": 4200,
      "price": 10.5,
      "amount": 44100.0,
      "cost": 61.603649999999995,
      "funds_after": 90599.65220780097
    },
    {
      "time": "2025-09-10 14:00:00",
      "code": "HK.02382",
      "action": "SELL",
      "qty": 300,
      "price": 81.25,
      "amount": 24375.0,
      "cost": 34.177187499999995,
      "funds_after": 114940.47502030098
    },
    {
      "time": "2025-09-15 14:00:00",
      "code": "HK.02382",
      "action": "BUY",
      "qty": 700,
      "price": 80.75,
      "amount": 56525.0,
      "cost": 78.2816625,
      "funds_after": 58337.19335780098
    },
    {
      "time": "2025-09-17 10:00:00",
      "code": "HK.02382",
      "action": "SELL",
      "qty": 700,
      "price": 82.05,
      "amount": 57435.0,
      "cost": 79.6242775,
      "funds_after": 115692.56908030098
    },
    {
      "time": "2025-09-18 14:30:00",
      "code": "HK.02382",
      "action": "BUY",
      "qty": 700,
      "price": 80.95,
      "amount": 56665.0,
      "cost": 78.3343725,
      "funds_after": 58949.23470780098
    },
    {
      "time": "2025-09-22 10:00:00",
      "code": "HK.02382",
      "action": "SELL",
      "qty": 700,
      "price": 84.45,
      "amount": 59115.0,
      "cost": 82.25679749999999,
      "funds_after": 117981.97791030098
    },
    {
      "time": "2025-09-23 10:00:00",
      "code": "HK.06683",
      "action": "BUY",
      "qty": 5300,
      "price": 11.03,
      "amount": 58459.0,
      "cost": 81.00981349999999,
      "funds_after": 59441.96809680098
    },
    {
      "time": "2025-09-23 14:00:00",
      "code": "HK.02382",
      "action": "BUY",
      "qty": 300,
      "price": 83.75,
      "amount": 25125.0,
      "cost": 35.4595625,
      "funds_after": 34281.50853430098
    },
    {
      "time": "2025-09-24 14:00:00",
      "code": "HK.02382",
      "action": "SELL",
      "qty": 300,
      "price": 85.25,
      "amount": 25575.0,
      "cost": 35.628987499999994,
      "funds_after": 59820.87954680098
    },
    {
      "time": "2025-09-25 14:00:00",
      "code": "HK.06683",
      "action": "SELL",
      "qty": 5300,
      "price": 10.97,
      "amount": 58141.0,
      "cost": 80.8900865,
      "funds_after": 117880.98946030097
    },
    {
      "time": "2025-09-26 10:00:00",
      "code": "HK.09961",
      "action": "BUY",
      "qty": 100,
      "price": 586.0,
      "amount": 58600.0,
      "cost": 81.0629,
      "funds_after": 59199.92656030098
    },
    {
      "time": "2025-09-29 10:30:00",
      "code": "HK.06683",
      "action": "BUY",
      "qty": 2700,
      "price": 10.65,
      "amount": 28755.0,
      "cost": 39.8262575,
      "funds_after": 30405.100302800976
    },
    {
      "time": "2025-09-30 13:30:00",
      "code": "HK.06683",
      "action": "SELL",
      "qty": 2700,
      "price": 10.83,
      "amount": 29241.0,
      "cost": 41.0092365,
      "funds_after": 59605.09106630098
    },
    {
      "time": "2025-10-03 10:00:00",
      "code": "HK.06683",
      "action": "BUY",
      "qty": 2800,
      "price": 10.47,
      "amount": 29316.0,
      "cost": 41.037473999999996,
      "funds_after": 30248.053592300977
    },
    {
      "time": "2025-10-09 10:00:00",
      "code": "HK.06683",
      "action": "SELL",
      "qty": 2800,
      "price": 10.58,
      "amount": 29624.0,
      "cost": 41.153436,
      "funds_after": 59830.90015630098
    },
    {
      "time": "2025-10-09 15:00:00",
      "code": "HK.06683",
      "action": "BUY",
      "qty": 2800,
      "price": 10.39,
      "amount": 29092.0,
      "cost": 40.953137999999996,
      "funds_after": 30697.94701830098
    },
    {
      "time": "2025-10-10 10:00:00",
      "code": "HK.02382",
      "action": "BUY",
      "qty": 100,
      "price": 85.85,
      "amount": 8585.0,
      "cost": 12.6567525,
      "funds_after": 22100.29026580098
    },
    {
      "time": "2025-10-13 11:00:00",
      "code": "HK.02382",
      "action": "SELL",
      "qty": 100,
      "price": 79.8,
      "amount": 7980.0,
      "cost": 11.61047,
      "funds_after": 30068.67979580098
    },
    {
      "time": "2025-10-13 11:30:00",
      "code": "HK.09961",
      "action": "SELL",
      "qty": 100,
      "price": 544.0,
      "amount": 54400.0,
      "cost": 75.48159999999999,
      "funds_after": 84393.19819580099
    },
    {
      "time": "2025-10-13 11:30:00",
      "code": "HK.02382",
      "action": "BUY",
      "qty": 500,
      "price": 78.55,
      "amount": 39275.0,
      "cost": 54.7870375,
      "funds_after": 45063.41115830099
    },
    {
      "time": "2025-10-14 10:00:00",
      "code": "HK.06683",
      "action": "SELL",
      "qty": 2800,
      "price": 10.16,
      "amount": 28448.0,
      "cost": 39.710671999999995,
      "funds_after": 73471.70048630098
    },
    {
      "time": "2025-10-14 13:30:00",
      "code": "HK.06683",
      "action": "BUY",
      "qty": 3700,
      "price": 9.92,
      "amount": 36704.0,
      "cost": 50.819056,
      "funds_after": 36716.88143030098
    },
    {
      "time": "2025-10-24 10:00:00",
      "code": "HK.06683",
      "action": "SELL",
      "qty": 3700,
      "price": 9.59,
      "amount": 35483.0,
      "cost": 49.3593495,
      "funds_after": 72150.52208080098
    },
    {
      "time": "2025-10-24 14:00:00",
      "code": "HK.06683",
      "action": "BUY",
      "qty": 3800,
      "price": 9.37,
      "amount": 35606.0,
      "cost": 49.40565899999999,
      "funds_after": 36495.11642180098
    },
    {
      "time": "2025-11-03 10:00:00",
      "code": "HK.02382",
      "action": "SELL",
      "qty": 500,
      "price": 73.25,
      "amount": 36625.0,
      "cost": 50.7893125,
      "funds_after": 73069.32710930098
    },
    {
      "time": "2025-11-03 10:00:00",
      "code": "HK.02382",
      "action": "BUY",
      "qty": 400,
      "price": 73.25,
      "amount": 29300.0,
      "cost": 41.03145,
      "funds_after": 43728.29565930099
    },
    {
      "time": "2025-11-05 11:00:00",
      "code": "HK.02382",
      "action": "SELL",
      "qty": 400,
      "price": 67.95,
      "amount": 27180.0,
      "cost": 38.23327,
      "funds_after": 70870.06238930099
    },
    {
      "time": "2025-11-06 11:00:00",
      "code": "HK.06683",
      "action": "SELL",
      "qty": 3800,
      "price": 9.0,
      "amount": 34200.0,
      "cost": 47.87629999999999,
      "funds_after": 105022.18608930099
    },
    {
      "time": "2025-11-06 11:30:00",
      "code": "HK.06683",
      "action": "BUY",
      "qty": 5800,
      "price": 8.98,
      "amount": 52084.0,
      "cost": 72.60962599999999,
      "funds_after": 52865.57646330099
    },
    {
      "time": "2025-11-07 10:00:00",
      "code": "HK.02382",
      "action": "BUY",
      "qty": 300,
      "price": 68.25,
      "amount": 20475.0,
      "cost": 28.7088375,
      "funds_after": 32361.86762580099
    },
    {
      "time": "2025-11-11 10:00:00",
      "code": "HK.06683",
      "action": "SELL",
      "qty": 5800,
      "price": 8.16,
      "amount": 47328.0,
      "cost": 65.81899200000001,
      "funds_after": 79624.048633801
    },
    {
      "time": "2025-11-11 10:00:00",
      "code": "HK.02382",
      "action": "SELL",
      "qty": 300,
      "price": 70.15,
      "amount": 21045.0,
      "cost": 29.923442499999997,
      "funds_after": 100639.12519130099
    },
    {
      "time": "2025-11-11 10:00:00",
      "code": "HK.06683",
      "action": "BUY",
      "qty": 6100,
      "price": 8.16,
      "amount": 49776.0,
      "cost": 68.740664,
      "funds_after": 50794.384527300994
    },
    {
      "time": "2025-11-11 13:30:00",
      "code": "HK.02382",
      "action": "BUY",
      "qty": 300,
      "price": 69.05,
      "amount": 20715.0,
      "cost": 28.799197500000002,
      "funds_after": 30050.585329800993
    },
    {
      "time": "2025-11-13 10:00:00",
      "code": "HK.06683",
      "action": "SELL",
      "qty": 6100,
      "price": 7.47,
      "amount": 45567.0,
      "cost": 63.155975500000004,
      "funds_after": 75554.429354301
    },
    {
      "time": "2025-11-13 10:00:00",
      "code": "HK.06683",
      "action": "BUY",
      "qty": 2200,
      "price": 7.47,
      "amount": 16434.0,
      "cost": 23.187400999999998,
      "funds_after": 59097.241953300996
    },
    {
      "time": "2025-11-14 10:00:00",
      "code": "HK.06683",
      "action": "SELL",
      "qty": 2200,
      "price": 6.84,
      "amount": 15048.0,
      "cost": 21.665571999999997,
      "funds_after": 74123.576381301
    },
    {
      "time": "2025-11-14 10:00:00",
      "code": "HK.06683",
      "action": "BUY",
      "qty": 3500,
      "price": 6.84,
      "amount": 23940.0,
      "cost": 33.01341,
      "funds_after": 50150.562971301
    },
    {
      "time": "2025-11-20 13:30:00",
      "code": "HK.02382",
      "action": "SELL",
      "qty": 300,
      "price": 64.25,
      "amount": 19275.0,
      "cost": 27.2570375,
      "funds_after": 69398.30593380099
    },
    {
      "time": "2025-11-20 13:30:00",
      "code": "HK.02382",
      "action": "BUY",
      "qty": 500,
      "price": 64.25,
      "amount": 32125.0,
      "cost": 45.095062500000004,
      "funds_after": 37228.210871300995
    },
    {
      "time": "2025-12-01 14:30:00",
      "code": "HK.02382",
      "action": "SELL",
      "qty": 500,
      "price": 67.25,
      "amount": 33625.0,
      "cost": 46.6598125,
      "funds_after": 70806.551058801
    },
    {
      "time": "2025-12-03 10:00:00",
      "code": "HK.06683",
      "action": "SELL",
      "qty": 3500,
      "price": 6.36,
      "amount": 22260.0,
      "cost": 31.380889999999997,
      "funds_after": 93035.17016880099
    },
    {
      "time": "2025-12-03 10:00:00",
      "code": "HK.06683",
      "action": "BUY",
      "qty": 7300,
      "price": 6.36,
      "amount": 46428.0,
      "cost": 64.480142,
      "funds_after": 46542.69002680099
    },
    {
      "time": "2025-12-11 12:00:00",
      "code": "HK.02382",
      "action": "BUY",
      "qty": 300,
      "price": 66.4,
      "amount": 19920.0,
      "cost": 27.499879999999997,
      "funds_after": 26595.190146800993
    },
    {
      "time": "2025-12-12 10:00:00",
      "code": "HK.02382",
      "action": "SELL",
      "qty": 300,
      "price": 66.85,
      "amount": 20055.0,
      "cost": 28.5507075,
      "funds_after": 46621.639439301
    },
    {
      "time": "2025-12-15 10:00:00",
      "code": "HK.02382",
      "action": "BUY",
      "qty": 300,
      "price": 66.65,
      "amount": 19995.0,
      "cost": 27.528117499999997,
      "funds_after": 26599.111321801
    },
    {
      "time": "2025-12-16 10:00:00",
      "code": "HK.06683",
      "action": "SELL",
      "qty": 7300,
      "price": 5.81,
      "amount": 42413.0,
      "cost": 58.968494500000006,
      "funds_after": 68953.142827301
    },
    {
      "time": "2025-12-16 10:00:00",
      "code": "HK.06683",
      "action": "BUY",
      "qty": 5900,
      "price": 5.81,
      "amount": 34279.0,
      "cost": 47.906043499999996,
      "funds_after": 34626.236783800996
    },
    {
      "time": "2025-12-17 10:00:00",
      "code": "HK.02382",
      "action": "SELL",
      "qty": 300,
      "price": 66.2,
      "amount": 19860.0,
      "cost": 27.47729,
      "funds_after": 54458.759493801
    },
    {
      "time": "2025-12-18 14:30:00",
      "code": "HK.02382",
      "action": "BUY",
      "qty": 400,
      "price": 64.7,
      "amount": 25880.0,
      "cost": 35.74382,
      "funds_after": 28543.015673801
    },
    {
      "time": "2025-12-22 10:00:00",
      "code": "HK.02382",
      "action": "SELL",
      "qty": 400,
      "price": 66.0,
      "amount": 26400.0,
      "cost": 36.9396,
      "funds_after": 54906.076073801
    },
    {
      "time": "2025-12-29 13:30:00",
      "code": "HK.02382",
      "action": "BUY",
      "qty": 400,
      "price": 64.95,
      "amount": 25980.0,
      "cost": 35.78146999999999,
      "funds_after": 28890.294603800998
    },
    {
      "time": "2026-01-12 11:00:00",
      "code": "HK.06683",
      "action": "SELL",
      "qty": 5900,
      "price": 6.28,
      "amount": 37052.0,
      "cost": 51.950078,
      "funds_after": 65890.34452580099
    },
    {
      "time": "2026-01-13 14:30:00",
      "code": "HK.06683",
      "action": "BUY",
      "qty": 5200,
      "price": 6.3,
      "amount": 32760.0,
      "cost": 45.334140000000005,
      "funds_after": 33085.01038580099
    },
    {
      "time": "2026-01-14 12:00:00",
      "code": "HK.06683",
      "action": "SELL",
      "qty": 5200,
      "price": 6.64,
      "amount": 34528.0,
      "cost": 47.999792,
      "funds_after": 67565.01059380098
    },
    {
      "time": "2026-01-16 10:00:00",
      "code": "HK.02382",
      "action": "SELL",
      "qty": 400,
      "price": 66.4,
      "amount": 26560.000000000004,
      "cost": 36.99984,
      "funds_after": 94088.01075380098
    },
    {
      "time": "2026-01-19 10:00:00",
      "code": "HK.02382",
      "action": "BUY",
      "qty": 700,
      "price": 65.2,
      "amount": 45640.0,
      "cost": 63.18346,
      "funds_after": 48384.827293800976
    },
    {
      "time": "2026-01-19 14:00:00",
      "code": "HK.06683",
      "action": "BUY",
      "qty": 3800,
      "price": 6.31,
      "amount": 23978.0,
      "cost": 33.027717,
      "funds_after": 24373.799576800975
    },
    {
      "time": "2026-01-20 10:30:00",
      "code": "HK.06683",
      "action": "SELL",
      "qty": 3800,
      "price": 6.39,
      "amount": 24282.0,
      "cost": 34.14217299999999,
      "funds_after": 48621.65740380097
    },
    {
      "time": "2026-01-20 13:30:00",
      "code": "HK.02382",
      "action": "SELL",
      "qty": 700,
      "price": 66.4,
      "amount": 46480.00000000001,
      "cost": 64.49972,
      "funds_after": 95037.15768380098
    },
    {
      "time": "2026-01-20 16:00:00",
      "code": "HK.06683",
      "action": "BUY",
      "qty": 7600,
      "price": 6.22,
      "amount": 47272.0,
      "cost": 65.797908,
      "funds_after": 47699.35977580098
    },
    {
      "time": "2026-01-23 10:00:00",
      "code": "HK.06683",
      "action": "SELL",
      "qty": 7600,
      "price": 6.25,
      "amount": 47500.0,
      "cost": 65.88375,
      "funds_after": 95133.47602580098
    },
    {
      "time": "2026-01-26 10:00:00",
      "code": "HK.02382",
      "action": "BUY",
      "qty": 700,
      "price": 62.45,
      "amount": 43715.0,
      "cost": 60.4586975,
      "funds_after": 51358.01732830098
    },
    {
      "time": "2026-01-26 11:00:00",
      "code": "HK.06683",
      "action": "BUY",
      "qty": 4200,
      "price": 6.09,
      "amount": 25578.0,
      "cost": 35.630117000000006,
      "funds_after": 25744.38721130098
    },
    {
      "time": "2026-01-27 14:30:00",
      "code": "HK.02382",
      "action": "SELL",
      "qty": 700,
      "price": 63.35,
      "amount": 44345.0,
      "cost": 61.6958925,
      "funds_after": 70027.69131880098
    },
    {
      "time": "2026-02-02 10:00:00",
      "code": "HK.02382",
      "action": "BUY",
      "qty": 500,
      "price": 60.4,
      "amount": 30200.0,
      "cost": 42.3703,
      "funds_after": 39785.32101880098
    },
    {
      "time": "2026-02-03 10:30:00",
      "code": "HK.02382",
      "action": "SELL",
      "qty": 500,
      "price": 60.5,
      "amount": 30250.0,
      "cost": 42.389125,
      "funds_after": 69992.93189380098
    },
    {
      "time": "2026-02-04 10:00:00",
      "code": "HK.02382",
      "action": "BUY",
      "qty": 500,
      "price": 59.35,
      "amount": 29675.0,
      "cost": 41.1726375,
      "funds_after": 40276.75925630098
    },
    {
      "time": "2026-02-13 11:30:00",
      "code": "HK.06683",
      "action": "SELL",
      "qty": 4200,
      "price": 6.18,
      "amount": 25956.0,
      "cost": 35.772434,
      "funds_after": 66196.98682230098
    },
    {
      "time": "2026-02-16 12:00:00",
      "code": "HK.02382",
      "action": "SELL",
      "qty": 500,
      "price": 57.85,
      "amount": 28925.0,
      "cost": 39.89026249999999,
      "funds_after": 95082.09655980098
    },
    {
      "time": "2026-02-20 10:00:00",
      "code": "HK.06683",
      "action": "BUY",
      "qty": 8100,
      "price": 5.86,
      "amount": 47466.0,
      "cost": 65.870949,
      "funds_after": 47550.22561080098
    },
    {
      "time": "2026-02-23 10:00:00",
      "code": "HK.02382",
      "action": "BUY",
      "qty": 400,
      "price": 57.5,
      "amount": 23000.0,
      "cost": 31.659499999999998,
      "funds_after": 24518.56611080098
    },
    {
      "time": "2026-02-23 10:30:00",
      "code": "HK.06683",
      "action": "SELL",
      "qty": 8100,
      "price": 6.04,
      "amount": 48924.0,
      "cost": 67.419886,
      "funds_after": 73375.14622480098
    },
    {
      "time": "2026-02-25 16:00:00",
      "code": "HK.06683",
      "action": "BUY",
      "qty": 6000,
      "price": 6.06,
      "amount": 36360.0,
      "cost": 50.68954,
      "funds_after": 36964.45668480098
    },
    {
      "time": "2026-03-03 14:30:00",
      "code": "HK.02382",
      "action": "SELL",
      "qty": 400,
      "price": 53.45,
      "amount": 21380.0,
      "cost": 30.049570000000003,
      "funds_after": 58314.40711480098
    },
    {
      "time": "2026-03-03 14:30:00",
      "code": "HK.02382",
      "action": "BUY",
      "qty": 500,
      "price": 53.45,
      "amount": 26725.0,
      "cost": 37.0619625,
      "funds_after": 31552.345152300983
    },
    {
      "time": "2026-03-04 10:30:00",
      "code": "HK.06683",
      "action": "SELL",
      "qty": 6000,
      "price": 5.98,
      "amount": 35880.0,
      "cost": 49.50881999999999,
      "funds_after": 67382.83633230098
    },
    {
      "time": "2026-03-05 10:00:00",
      "code": "HK.02382",
      "action": "SELL",
      "qty": 500,
      "price": 54.2,
      "amount": 27100.0,
      "cost": 38.203149999999994,
      "funds_after": 94444.63318230098
    },
    {
      "time": "2026-03-05 11:30:00",
      "code": "HK.09961",
      "action": "BUY",
      "qty": 100,
      "price": 390.0,
      "amount": 39000.0,
      "cost": 53.6835,
      "funds_after": 55390.94968230098
    },
    {
      "time": "2026-03-05 14:00:00",
      "code": "HK.02382",
      "action": "BUY",
      "qty": 500,
      "price": 53.7,
      "amount": 26850.0,
      "cost": 37.109024999999995,
      "funds_after": 28503.84065730098
    },
    {
      "time": "2026-03-06 14:30:00",
      "code": "HK.02382",
      "action": "SELL",
      "qty": 500,
      "price": 55.25,
      "amount": 27625.0,
      "cost": 38.4008125,
      "funds_after": 56090.43984480098
    },
    {
      "time": "2026-03-10 10:00:00",
      "code": "HK.09961",
      "action": "SELL",
      "qty": 100,
      "price": 417.2,
      "amount": 41720.0,
      "cost": 57.70758,
      "funds_after": 97752.73226480099
    },
    {
      "time": "2026-03-10 16:00:00",
      "code": "HK.06683",
      "action": "BUY",
      "qty": 7400,
      "price": 6.56,
      "amount": 48544.0,
      "cost": 67.27681599999998,
      "funds_after": 49141.45544880099
    },
    {
      "time": "2026-03-13 11:00:00",
      "code": "HK.06683",
      "action": "SELL",
      "qty": 7400,
      "price": 7.3,
      "amount": 54020.0,
      "cost": 75.33853,
      "funds_after": 103086.11691880098
    },
    {
      "time": "2026-03-16 11:30:00",
      "code": "HK.06693",
      "action": "BUY",
      "qty": 1300,
      "price": 37.36,
      "amount": 48568.0,
      "cost": 67.285852,
      "funds_after": 54450.83106680098
    },
    {
      "time": "2026-03-17 10:00:00",
      "code": "HK.06693",
      "action": "SELL",
      "qty": 1300,
      "price": 38.96,
      "amount": 50648.0,
      "cost": 70.068972,
      "funds_after": 105028.76209480097
    },
    {
      "time": "2026-03-17 14:30:00",
      "code": "HK.09961",
      "action": "BUY",
      "qty": 100,
      "price": 408.8,
      "amount": 40880.0,
      "cost": 56.39131999999999,
      "funds_after": 64092.37077480097
    },
    {
      "time": "2026-03-18 13:30:00",
      "code": "HK.09961",
      "action": "SELL",
      "qty": 100,
      "price": 414.2,
      "amount": 41420.0,
      "cost": 57.59463,
      "funds_after": 105454.77614480097
    },
    {
      "time": "2026-03-18 16:00:00",
      "code": "HK.02382",
      "action": "BUY",
      "qty": 900,
      "price": 56.95,
      "amount": 51255.0,
      "cost": 71.29750749999998,
      "funds_after": 54128.47863730097
    },
    {
      "time": "2026-03-20 00:00:00",
      "code": "HK.02600",
      "action": "BUY",
      "qty": 2300,
      "price": 11.49,
      "amount": 26427.0,
      "cost": 36.9497655,
      "funds_after": 27664.52887180097
    },
    {
      "time": "2026-03-23 10:00:00",
      "code": "HK.02600",
      "action": "SELL",
      "qty": 2300,
      "price": 10.61,
      "amount": 24403.0,
      "cost": 34.187729499999996,
      "funds_after": 52033.34114230097
    },
    {
      "time": "2026-03-23 10:00:00",
      "code": "HK.02600",
      "action": "BUY",
      "qty": 2400,
      "price": 10.61,
      "amount": 25464.0,
      "cost": 35.587196,
      "funds_after": 26533.753946300967
    },
    {
      "time": "2026-03-23 11:30:00",
      "code": "HK.02382",
      "action": "SELL",
      "qty": 900,
      "price": 52.85,
      "amount": 47565.0,
      "cost": 65.90822250000001,
      "funds_after": 74032.84572380097
    },
    {
      "time": "2026-03-23 14:30:00",
      "code": "HK.02382",
      "action": "BUY",
      "qty": 700,
      "price": 52.25,
      "amount": 36575.0,
      "cost": 50.770487499999994,
      "funds_after": 37407.075236300974
    }
  ],
  "cost_statistics": {
    "total_cost": 8864.124762599058,
    "total_commission": 1914.2530199992498,
    "total_stamp_duty": 6462,
    "total_trading_fee": 0,
    "total_clearing_fee": 0
  },
  "win_rate": 0.39080459770114945,
  "avg_profit": 4524.173976951504,
  "avg_loss": 4806.22685789054,
  "profit_loss_ratio": 0.9413151128153721,
  "annualized_return": -0.005539247636990319,
  "trades_per_month": 14.465753424657535,
  "stop_loss_triggered": 27
}